{
    "key": "group_57fc6d54575a7",
    "title": "News",
    "fields": [
        {
            "key": "field_57fc6d5d23507",
            "label": "External URL",
            "name": "link_url",
            "type": "url",
            "instructions": "",
            "required": 1,
            "conditional_logic": 0,
            "wrapper": {
                "width": "",
                "class": "",
                "id": ""
            },
            "default_value": "",
            "placeholder": ""
        },
        {
            "key": "field_5825743bbd336",
            "label": "Sticky",
            "name": "sticky",
            "type": "checkbox",
            "instructions": "",
            "required": 0,
            "conditional_logic": 0,
            "wrapper": {
                "width": "",
                "class": "",
                "id": ""
            },
            "choices": {
                "1": "Place this item at the top of lists wherever it appears"
            },
            "default_value": [],
            "layout": "vertical",
            "toggle": 0,
            "return_format": "value"
        }
    ],
    "location": [
        [
            {
                "param": "post_type",
                "operator": "==",
                "value": "news"
            }
        ]
    ],
    "menu_order": 0,
    "position": "normal",
    "style": "default",
    "label_placement": "top",
    "instruction_placement": "label",
    "hide_on_screen": "",
    "active": 1,
    "description": "",
    "modified": 1478849629
}